ctlepy/__init__.py
ctlepy/enum_generator.py
ctlepy/file_checker.py
ctlepy/formatted_output.py
ctlepy-1.7.2.dist-info/licenses/LICENSE
ctlepy-1.7.2.dist-info/METADATA
ctlepy-1.7.2.dist-info/WHEEL
ctlepy-1.7.2.dist-info/top_level.txt
ctlepy-1.7.2.dist-info/RECORD
