Metadata-Version: 2.4
Name: ctlepy
Version: 1.7.2
Summary: Python package for ctle
Home-page: https://github.com/Cooolrik/ctle
Author: Ulrik Lindahl
Project-URL: Bug Tracker, https://github.com/Cooolrik/ctle
Project-URL: repository, https://github.com/Cooolrik/ctle
Classifier: Programming Language :: Python :: 3
Classifier: License :: OSI Approved :: MIT License
Classifier: Operating System :: OS Independent
Requires-Python: >=3.10
License-File: LICENSE
Dynamic: license-file
